Metadata-Version: 1.1
Name: descolors
Version: 0.1.0
Summary: Standard color scheme for plotting DES/DECam filters.
Home-page: https://github.com/kadrlica/descolors
Author: Alex Drlica-Wagner
Author-email: kadrlica@fnal.gov
License: UNKNOWN
Keywords: des
Platform: any
Classifier: Programming Language :: Python
Classifier: Development Status :: 2 - Pre-Alpha
Classifier: Natural Language :: English
Classifier: Intended Audience :: Science/Research
